spire/__init__.py
spire/barcode/BarCodeFormatException.py
spire/barcode/BarCodeGenerator.py
spire/barcode/BarCodeReadType.py
spire/barcode/BarCodeType.py
spire/barcode/BarcodeInfo.py
spire/barcode/BarcodeScanner.py
spire/barcode/BarcodeSettings.py
spire/barcode/BitArrayHelper.py
spire/barcode/Blacklist.py
spire/barcode/CheckSumMode.py
spire/barcode/CodabarChar.py
spire/barcode/Code128SetMode.py
spire/barcode/Color.py
spire/barcode/Common.py
spire/barcode/CultureInfo.py
spire/barcode/DashStyle.py
spire/barcode/DataMatrixSymbolShape.py
spire/barcode/DateTime.py
spire/barcode/DotfuscatorAttribute.py
spire/barcode/EmfType.py
spire/barcode/Encoding.py
spire/barcode/FontStyle.py
spire/barcode/GraphicsUnit.py
spire/barcode/IBarcodeSettings.py
spire/barcode/IChecksum.py
spire/barcode/ITF14BorderType.py
spire/barcode/ImageFormat.py
spire/barcode/License.py
spire/barcode/PackageAttribute.py
spire/barcode/Pdf417DataMode.py
spire/barcode/Pdf417ECL.py
spire/barcode/PixelFormat.py
spire/barcode/Point.py
spire/barcode/PointF.py
spire/barcode/QRCodeDataMode.py
spire/barcode/QRCodeECL.py
spire/barcode/Rectangle.py
spire/barcode/RectangleF.py
spire/barcode/Regex.py
spire/barcode/RegexOptions.py
spire/barcode/ReleaseDateAttribute.py
spire/barcode/ResolutionType.py
spire/barcode/Size.py
spire/barcode/SizeF.py
spire/barcode/SpireObject.py
spire/barcode/Stream.py
spire/barcode/StringAlignment.py
spire/barcode/SymbologyType.py
spire/barcode/TextRenderingHint.py
spire/barcode/TimeSpan.py
spire/barcode/__init__.py
spire/barcode/lib/Spire.Barcode.Base.dll
spire/barcode/lib/__init__.py
spire/barcode/lib/libSkiaSharp.dll
spire_barcode-7.2.12.dist-info/METADATA
spire_barcode-7.2.12.dist-info/WHEEL
spire_barcode-7.2.12.dist-info/top_level.txt
spire_barcode-7.2.12.dist-info/RECORD
